rangeSlicing.py
rangeSlicing-0.1.3.data/scripts/rangeSlicing
rangeSlicing-0.1.3.data/scripts/rangeSlicing.py
tests/__init__.py
rangeSlicing-0.1.3.dist-info/LICENSE
rangeSlicing-0.1.3.dist-info/METADATA
rangeSlicing-0.1.3.dist-info/WHEEL
rangeSlicing-0.1.3.dist-info/top_level.txt
rangeSlicing-0.1.3.dist-info/RECORD
